yaslackmessenger/__init__.py
yaslackmessenger-0.0.2.dist-info/METADATA
yaslackmessenger-0.0.2.dist-info/WHEEL
yaslackmessenger-0.0.2.dist-info/top_level.txt
yaslackmessenger-0.0.2.dist-info/RECORD
