Metadata-Version: 2.1
Name: yaslackmessenger
Version: 0.0.2
Summary: Yet Another Slack Messenger
Home-page: https://gitlab.com/cristianowa/yaslackmessenger
Author: Cristiano W. Araujo
Author-email: cristianowerneraraujo@gmail.com
License: UNKNOWN
Download-URL: https://gitlab.com/cristianowa/yaslackmessenger/-/archive/0.0.2/yaslackmessenger-0.0.2.zip
Keywords: slack,webhooks
Platform: UNKNOWN
